Workbook
Name Slicer_Category: #N/A
Name Slicer_City: #N/A
Name Slicer_Customer_Segment: #N/A
Name Slicer_WEEKDAYS: #N/A

Sheet Sheet2
A1: Order_ID | B1: Order_Date | C1: Customer_Name | D1: Customer_Type | E1: Customer_Segment | F1: City | G1: Pincode | H1: Payment_Method | I1: SKU | J1: Product_Name | K1: Category | L1: Qty | M1: Price | N1: Discount | O1: Subtotal | P1: Tax | Q1: Delivery_Fee | R1: Surge_Fee | S1: Sales | T1: Delivery_Time | U1: WEEKDAYS
A2: O0001 | B2: 08-02-2025 | C2: Cust_0 | D2: Bulk | E2: Bakery | F2: Mumbai | G2: 532498 | H2: Wallet | I2: SKU0 | J2: Product_0 | K2: Veg | L2: 2 | M2: 94.25 | N2: 9.43 | O2: 179.07 | P2: 8.95 | Q2: 0 | R2: 10 | S2: 198.02 | T2: 12 | U2: =TEXT(B2,"dddd") -> Saturday
A3: O0002 | B3: 21-02-2025 | C3: Cust_1 | D3: Bulk | E3: Bakery | F3: Mumbai | G3: 157545 | H3: Upi | I3: SKU1 | J3: Product_1 | K3: Essentials | L3: 1 | M3: 18.45 | N3: 1.84 | O3: 16.61 | P3: 0.83 | Q3: 0 | R3: 0 | S3: 17.44 | T3: 24.67 | U3: =TEXT(B3,"dddd") -> Friday | W3: countblank (CITY) | X3: =COUNTBLANK(F2:F1499) -> 0
A4: O0005 | B4: 12-02-2025 | C4: Cust_4 | D4: Bulk | E4: Bakery | F4: Bangalore | G4: 429670 | H4: Upi | I4: SKU4 | J4: Product_4 | K4: Snacks | L4: 6 | M4: 52.47 | N4: 7.87 | O4: 306.95 | P4: 15.35 | Q4: 0 | R4: 0 | S4: 322.3 | T4: 23 | U4: =TEXT(B4,"dddd") -> Wednesday | X4: =28/1499 -> 0.018679119
A5: O0006 | B5: 08-01-2025 | C5: Cust_5 | D5: Bulk | E5: Café | F5: Delhi | G5: 258768 | H5: Netbanking | I5: SKU5 | J5: Product_5 | K5: Other | L5: 5 | M5: 78.11 | N5: 3.91 | O5: 386.64 | P5: 19.33 | Q5: 30 | R5: 15 | S5: 450.97 | T5: 18 | U5: =TEXT(B5,"dddd") -> Wednesday | W5: AVERAGE | X5: =AVERAGE(T:T) -> 24.671215
A6: O0007 | B6: 21-01-2025 | C6: Cust_6 | D6: Bulk | E6: Bakery | F6: Bangalore | G6: 776926 | H6: Upi | I6: SKU6 | J6: Product_6 | K6: Bakery | L6: 1 | M6: 103.87 | N6: 5.19 | O6: 98.68 | P6: 4.93 | Q6: 20 | R6: 0 | S6: 123.61 | T6: 13 | U6: =TEXT(B6,"dddd") -> Tuesday
A7: O0008 | B7: 08-02-2025 | C7: Cust_7 | D7: Bulk | E7: Bakery | F7: Delhi | G7: 233554 | H7: Cod | I7: SKU7 | J7: Product_7 | K7: Frozen | L7: 3 | M7: 129.5 | N7: 12.95 | O7: 375.55 | P7: 18.78 | Q7: 20 | R7: 10 | S7: 424.33 | T7: 16 | U7: =TEXT(B7,"dddd") -> Saturday
A8: O0009 | B8: 27-02-2025 | C8: Cust_8 | D8: Bulk | E8: Office | F8: Mumbai | G8: 159676 | H8: Upi | I8: SKU8 | J8: Product_8 | K8: Snacks | L8: 1 | M8: 131.89 | N8: 0 | O8: 131.89 | P8: 6.59 | Q8: 10 | R8: 0 | S8: 148.48 | T8: 23 | U8: =TEXT(B8,"dddd") -> Thursday
A9: O0010 | B9: 19-01-2025 | C9: Cust_9 | D9: Bulk | E9: Cloud Kitchen | F9: Delhi | G9: 688365 | H9: Upi | I9: SKU9 | J9: Product_9 | K9: Dairy | L9: 1 | M9: 207.92 | N9: 20.79 | O9: 187.13 | P9: 9.36 | Q9: 30 | R9: 0 | S9: 226.49 | T9: 17 | U9: =TEXT(B9,"dddd") -> Sunday
A10: O0011 | B10: 23-01-2025 | C10: Cust_10 | D10: New | E10: Household | F10: Delhi | G10: 481915 | H10: Wallet | I10: SKU10 | J10: Product_10 | K10: Dairy | L10: 3 | M10: 134.09 | N10: 13.41 | O10: 388.86 | P10: 19.44 | Q10: 20 | R10: 0 | S10: 428.3 | T10: 24.67 | U10: =TEXT(B10,"dddd") -> Thursday
A11: O0012 | B11: 11-01-2025 | C11: Cust_11 | D11: Bulk | E11: Cloud Kitchen | F11: Delhi | G11: 951587 | H11: Upi | I11: SKU11 | J11: Product_11 | K11: Fruits | L11: 6 | M11: 86.17 | N11: 0 | O11: 517.02 | P11: 25.85 | Q11: 10 | R11: 5 | S11: 557.87 | T11: 10 | U11: =TEXT(B11,"dddd") -> Saturday
A12: O0013 | B12: 11-01-2025 | C12: Cust_12 | D12: Bulk | E12: Cloud Kitchen | F12: Mumbai | G12: 962061 | H12: Upi | I12: SKU12 | J12: Product_12 | K12: Frozen | L12: 3 | M12: 104.71 | N12: 5.24 | O12: 308.89 | P12: 15.44 | Q12: 10 | R12: 20 | S12: 354.33 | T12: 16 | U12: =TEXT(B12,"dddd") -> Saturday
A13: O0014 | B13: 24-01-2025 | C13: Cust_13 | D13: Bulk | E13: Office | F13: Mumbai | G13: 730235 | H13: Card | I13: SKU13 | J13: Product_13 | K13: Baby | L13: 4 | M13: 204.9 | N13: 20.49 | O13: 799.11 | P13: 39.96 | Q13: 0 | R13: 0 | S13: 839.07 | T13: 24.67 | U13: =TEXT(B13,"dddd") -> Friday
A14: O0015 | B14: 22-02-2025 | C14: Cust_14 | D14: Returning | E14: Household | F14: Mumbai | G14: 605815 | H14: Upi | I14: SKU14 | J14: Product_14 | K14: Bakery | L14: 3 | M14: 193.33 | N14: 0 | O14: 579.99 | P14: 29 | Q14: 30 | R14: 20 | S14: 658.99 | T14: 3 | U14: =TEXT(B14,"dddd") -> Saturday
A15: O0016 | B15: 05-02-2025 | C15: Cust_15 | D15: Bulk | E15: Tea Stall | F15: Bangalore | G15: 434402 | H15: Wallet | I15: SKU15 | J15: Product_15 | K15: Fruits | L15: 3 | M15: 35.35 | N15: 3.54 | O15: 102.51 | P15: 5.13 | Q15: 30 | R15: 0 | S15: 137.64 | T15: 25 | U15: =TEXT(B15,"dddd") -> Wednesday
A16: O0017 | B16: 09-02-2025 | C16: Cust_16 | D16: Bulk | E16: Tea Stall | F16: Delhi | G16: 427073 | H16: Cod | I16: SKU16 | J16: Product_16 | K16: Snacks | L16: 2 | M16: 128.59 | N16: 6.43 | O16: 250.75 | P16: 12.54 | Q16: 0 | R16: 5 | S16: 268.29 | T16: 34 | U16: =TEXT(B16,"dddd") -> Sunday
A17: O0018 | B17: 24-01-2025 | C17: Cust_17 | D17: Bulk | E17: Tea Stall | F17: Mumbai | G17: 416915 | H17: Upi | I17: SKU17 | J17: Product_17 | K17: Baby | L17: 5 | M17: 145.22 | N17: 7.26 | O17: 718.84 | P17: 35.94 | Q17: 20 | R17: 5 | S17: 779.78 | T17: 24.67 | U17: =TEXT(B17,"dddd") -> Friday
A18: O0019 | B18: 03-01-2025 | C18: Cust_18 | D18: Bulk | E18: Bakery | F18: Bangalore | G18: 890857 | H18: Phonepe | I18: SKU18 | J18: Product_18 | K18: Essentials | L18: 1 | M18: 156.96 | N18: 23.54 | O18: 133.42 | P18: 6.67 | Q18: 10 | R18: 5 | S18: 155.09 | T18: 18 | U18: =TEXT(B18,"dddd") -> Friday
A19: O0020 | B19: 22-01-2025 | C19: Cust_19 | D19: Bulk | E19: Office | F19: Bangalore | H19: Upi | I19: SKU19 | J19: Product_19 | K19: Essentials | L19: 2 | M19: 19.81 | N19: 0 | O19: 39.62 | P19: 1.98 | Q19: 20 | R19: 20 | S19: 81.6 | T19: 42 | U19: =TEXT(B19,"dddd") -> Wednesday
A20: O0021 | B20: 22-02-2025 | C20: Cust_20 | D20: Bulk | E20: Café | F20: Mumbai | G20: 727433 | H20: Upi | I20: SKU20 | J20: Product_20 | K20: Beverages | L20: 3 | M20: 164.88 | N20: 16.49 | O20: 478.15 | P20: 23.91 | Q20: 30 | R20: 10 | S20: 542.06 | T20: 24.67 | U20: =TEXT(B20,"dddd") -> Saturday
A21: O0022 | B21: 02-01-2025 | C21: Cust_21 | D21: Bulk | E21: Bakery | F21: Bangalore | G21: 756639 | H21: Upi | I21: SKU21 | J21: Product_21 | K21: Beverages | L21: 2 | M21: 185.31 | N21: 27.8 | O21: 342.82 | P21: 17.14 | Q21: 10 | R21: 0 | S21: 369.96 | T21: 32 | U21: =TEXT(B21,"dddd") -> Thursday
A22: O0023 | B22: 24-01-2025 | C22: Cust_22 | D22: Bulk | E22: Café | F22: Delhi | G22: 881817 | H22: Netbanking | I22: SKU22 | J22: Product_22 | K22: Veg | L22: 1 | M22: 4.92 | N22: 0.25 | O22: 4.67 | P22: 0.23 | Q22: 10 | R22: 15 | S22: 29.9 | T22: 41 | U22: =TEXT(B22,"dddd") -> Friday
A23: O0024 | B23: 13-02-2025 | C23: Cust_23 | D23: Bulk | E23: Bakery | F23: Bangalore | G23: 607606 | H23: Upi | I23: SKU23 | J23: Product_23 | K23: Fruits | L23: 1 | M23: 143.95 | N23: 7.2 | O23: 136.75 | P23: 6.84 | Q23: 30 | R23: 5 | S23: 178.59 | T23: 27 | U23: =TEXT(B23,"dddd") -> Thursday
A24: O0025 | B24: 30-01-2025 | C24: Cust_24 | D24: New | E24: Household | F24: Bangalore | G24: 127856 | H24: Gpay | I24: SKU24 | J24: Product_24 | K24: Beverages | L24: 3 | M24: 99.86 | N24: 14.98 | O24: 284.6 | P24: 14.23 | Q24: 20 | R24: 5 | S24: 323.83 | T24: 38 | U24: =TEXT(B24,"dddd") -> Thursday
A25: O0026 | B25: 07-02-2025 | C25: Cust_25 | D25: Bulk | E25: Office | F25: Delhi | G25: 248757 | H25: Upi | I25: SKU25 | J25: Product_25 | K25: Baby | L25: 3 | M25: 17.39 | N25: 0 | O25: 52.17 | P25: 2.61 | Q25: 0 | R25: 10 | S25: 64.78 | T25: 11 | U25: =TEXT(B25,"dddd") -> Friday
A26: O0027 | B26: 02-01-2025 | C26: Cust_26 | D26: Bulk | E26: Tea Stall | F26: Mumbai | G26: 436676 | H26: Upi | I26: SKU26 | J26: Product_26 | K26: Beverages | L26: 2 | M26: 42.69 | N26: 0 | O26: 85.38 | P26: 4.27 | Q26: 10 | R26: 15 | S26: 114.65 | T26: 26 | U26: =TEXT(B26,"dddd") -> Thursday
A27: O0028 | B27: 01-03-2025 | C27: Cust_27 | D27: Bulk | E27: Bakery | F27: Mumbai | G27: 752665 | H27: Upi | I27: SKU27 | J27: Product_27 | K27: Essentials | L27: 3 | M27: 61.3 | N27: 0 | O27: 183.9 | P27: 9.19 | Q27: 30 | R27: 15 | S27: 238.09 | T27: 45 | U27: =TEXT(B27,"dddd") -> Saturday
A28: O0029 | B28: 21-01-2025 | C28: Cust_28 | D28: Bulk | E28: Office | F28: Bangalore | G28: 816756 | H28: Upi | I28: SKU28 | J28: Product_28 | K28: Fruits | L28: 4 | M28: 86.32 | N28: 4.32 | O28: 340.96 | P28: 17.05 | Q28: 0 | R28: 0 | S28: 358.01 | T28: 28 | U28: =TEXT(B28,"dddd") -> Tuesday
A29: O0030 | B29: 02-02-2025 | C29: Cust_29 | D29: Bulk | E29: Tea Stall | F29: Delhi | G29: 672212 | H29: Phonepe | I29: SKU29 | J29: Product_29 | K29: Fruits | L29: 1 | M29: 65.42 | N29: 6.54 | O29: 58.88 | P29: 2.94 | Q29: 0 | R29: 5 | S29: 66.82 | T29: 41 | U29: =TEXT(B29,"dddd") -> Sunday
A30: O0031 | B30: 12-01-2025 | C30: Cust_30 | D30: Returning | E30: Household | F30: Bangalore | G30: 791757 | H30: Cod | I30: SKU30 | J30: Product_30 | K30: Veg | L30: 6 | M30: 9.55 | N30: 1.43 | O30: 55.87 | P30: 2.79 | Q30: 20 | R30: 10 | S30: 88.66 | T30: 12 | U30: =TEXT(B30,"dddd") -> Sunday
A31: O0032 | B31: 27-02-2025 | C31: Cust_31 | D31: Bulk | E31: Cloud Kitchen | F31: Bangalore | G31: 322320 | H31: Phonepe | I31: SKU31 | J31: Product_31 | K31: Dairy | L31: 2 | M31: 131.91 | N31: 13.19 | O31: 250.63 | P31: 12.53 | Q31: 0 | R31: 15 | S31: 278.16 | T31: 22 | U31: =TEXT(B31,"dddd") -> Thursday
... A57: O0058 | B57: 04-01-2025 | C57: Cust_57 | D57: Bulk | E57: Café | F57: Delhi | G57: 963561 | H57: Card | I57: SKU57 | J57: Product_57 | K57: Fruits | L57: 3 | M57: 190.03 | N57: 0 | O57: 570.09 | P57: 28.5 | Q57: 10 | R57: 20 | S57: 628.59 | T57: 41 | U57: =TEXT(B57,"dddd") -> Saturday
A58: O0059 | B58: 25-01-2025 | C58: Cust_58 | D58: Bulk | E58: Tea Stall | F58: Bangalore | H58: Card | I58: SKU58 | J58: Product_58 | K58: Frozen | L58: 2 | M58: 89.93 | N58: 4.5 | O58: 175.36 | P58: 8.77 | Q58: 10 | R58: 20 | S58: 214.13 | T58: 30 | U58: =TEXT(B58,"dddd") -> Saturday
A59: O0060 | B59: 01-03-2025 | C59: Cust_59 | D59: Bulk | E59: Office | F59: Mumbai | G59: 249369 | H59: Wallet | I59: SKU59 | J59: Product_59 | K59: Snacks | L59: 5 | M59: 125.79 | N59: 0 | O59: 628.95 | P59: 31.45 | Q59: 30 | R59: 10 | S59: 700.4 | T59: 10 | U59: =TEXT(B59,"dddd") -> Saturday
A60: O0061 | B60: 14-01-2025 | C60: Cust_60 | D60: Bulk | E60: Café | F60: Bangalore | G60: 474999 | H60: Card | I60: SKU60 | J60: Product_60 | K60: Frozen | L60: 1 | M60: 130.64 | N60: 0 | O60: 130.64 | P60: 6.53 | Q60: 10 | R60: 5 | S60: 152.17 | T60: 32 | U60: =TEXT(B60,"dddd") -> Tuesday
A61: O0062 | B61: 19-02-2025 | C61: Cust_61 | D61: Bulk | E61: Office | F61: Delhi | G61: 893719 | H61: Wallet | I61: SKU61 | J61: Product_61 | K61: Dairy | L61: 5 | M61: 114.77 | N61: 17.22 | O61: 556.63 | P61: 27.83 | Q61: 0 | R61: 15 | S61: 599.46 | T61: 34 | U61: =TEXT(B61,"dddd") -> Wednesday
A62: O0063 | B62: 27-02-2025 | C62: Cust_62 | D62: Bulk | E62: Cloud Kitchen | F62: Mumbai | G62: 426916 | H62: Netbanking | I62: SKU62 | J62: Product_62 | K62: Veg | L62: 1 | M62: 67.3 | N62: 3.37 | O62: 63.93 | P62: 3.2 | Q62: 10 | R62: 20 | S62: 97.13 | T62: 30 | U62: =TEXT(B62,"dddd") -> Thursday
A63: O0064 | B63: 09-01-2025 | C63: Cust_63 | D63: Bulk | E63: Tea Stall | F63: Mumbai | G63: 658030 | H63: Card | I63: SKU63 | J63: Product_63 | K63: Veg | L63: 5 | M63: 65.64 | N63: 0 | O63: 328.2 | P63: 16.41 | Q63: 0 | R63: 0 | S63: 344.61 | T63: 34 | U63: =TEXT(B63,"dddd") -> Thursday
A64: O0065 | B64: 26-01-2025 | C64: Cust_64 | D64: Bulk | E64: Tea Stall | F64: Bangalore | G64: 972388 | H64: Upi | I64: SKU64 | J64: Product_64 | K64: Dairy | L64: 3 | M64: 82.14 | N64: 12.32 | O64: 234.1 | P64: 11.71 | Q64: 0 | R64: 0 | S64: 245.81 | T64: 31 | U64: =TEXT(B64,"dddd") -> Sunday
A65: O0066 | B65: 22-02-2025 | C65: Cust_65 | D65: Bulk | E65: Office | F65: Mumbai | G65: 228322 | H65: Netbanking | I65: SKU65 | J65: Product_65 | K65: Fruits | L65: 1 | M65: 122.6 | N65: 0 | O65: 122.6 | P65: 6.13 | Q65: 10 | R65: 10 | S65: 148.73 | T65: 35 | U65: =TEXT(B65,"dddd") -> Saturday
A66: O0067 | B66: 02-01-2025 | C66: Cust_66 | D66: Bulk | E66: Café | F66: Bangalore | G66: 186231 | H66: Card | I66: SKU66 | J66: Product_66 | K66: Dairy | L66: 5 | M66: 52.09 | N66: 0 | O66: 260.45 | P66: 13.02 | Q66: 10 | R66: 0 | S66: 283.47 | T66: 29 | U66: =TEXT(B66,"dddd") -> Thursday
A67: O0068 | B67: 20-01-2025 | C67: Cust_67 | D67: Bulk | E67: Cloud Kitchen | F67: Bangalore | G67: 590042 | H67: Cod | I67: SKU67 | J67: Product_67 | K67: Essentials | L67: 4 | M67: 155.44 | N67: 0 | O67: 621.76 | P67: 31.09 | Q67: 10 | R67: 15 | S67: 677.85 | T67: 36 | U67: =TEXT(B67,"dddd") -> Monday
A68: O0069 | B68: 28-01-2025 | C68: Cust_68 | D68: Bulk | E68: Office | F68: Delhi | G68: 153947 | H68: Upi | I68: SKU68 | J68: Product_68 | K68: Bakery | L68: 3 | M68: 162.9 | N68: 16.29 | O68: 472.41 | P68: 23.62 | Q68: 20 | R68: 5 | S68: 521.03 | T68: 28 | U68: =TEXT(B68,"dddd") -> Tuesday
A69: O0070 | B69: 16-02-2025 | C69: Cust_69 | D69: Bulk | E69: Café | F69: Delhi | H69: Gpay | I69: SKU69 | J69: Product_69 | K69: Baby | L69: 1 | M69: 109.97 | N69: 5.5 | O69: 104.47 | P69: 5.22 | Q69: 30 | R69: 5 | S69: 144.69 | T69: 26 | U69: =TEXT(B69,"dddd") -> Sunday
A70: O0071 | B70: 01-03-2025 | C70: Cust_70 | D70: Bulk | E70: Office | F70: Bangalore | G70: 716412 | H70: Wallet | I70: SKU70 | J70: Product_70 | K70: Other | L70: 3 | M70: 110.85 | N70: 0 | O70: 332.55 | P70: 16.63 | Q70: 30 | R70: 5 | S70: 384.18 | T70: 29 | U70: =TEXT(B70,"dddd") -> Saturday
A71: O0072 | B71: 07-01-2025 | C71: Cust_71 | D71: Bulk | E71: Tea Stall | F71: Mumbai | G71: 175418 | H71: Upi | I71: SKU71 | J71: Product_71 | K71: Fruits | L71: 3 | M71: 73.07 | N71: 3.65 | O71: 215.56 | P71: 10.78 | Q71: 20 | R71: 10 | S71: 256.34 | T71: 18 | U71: =TEXT(B71,"dddd") -> Tuesday
A72: O0073 | B72: 13-02-2025 | C72: Cust_72 | D72: New | E72: Household | F72: Delhi | G72: 700530 | H72: Gpay | I72: SKU72 | J72: Product_72 | K72: Frozen | L72: 3 | M72: 125.4 | N72: 6.27 | O72: 369.93 | P72: 18.5 | Q72: 0 | R72: 10 | S72: 398.43 | T72: 22 | U72: =TEXT(B72,"dddd") -> Thursday
A73: O0074 | B73: 08-01-2025 | C73: Cust_73 | D73: Bulk | E73: Café | F73: Mumbai | G73: 244353 | H73: Gpay | I73: SKU73 | J73: Product_73 | K73: Frozen | L73: 3 | M73: 134.96 | N73: 20.24 | O73: 384.64 | P73: 19.23 | Q73: 30 | R73: 10 | S73: 443.87 | T73: 40 | U73: =TEXT(B73,"dddd") -> Wednesday
A74: O0075 | B74: 16-02-2025 | C74: Cust_74 | D74: Bulk | E74: Cloud Kitchen | F74: Mumbai | G74: 827955 | H74: Netbanking | I74: SKU74 | J74: Product_74 | K74: Snacks | L74: 5 | M74: 33.51 | N74: 1.68 | O74: 165.87 | P74: 8.29 | Q74: 20 | R74: 20 | S74: 214.16 | T74: 32 | U74: =TEXT(B74,"dddd") -> Sunday
A75: O0076 | B75: 04-02-2025 | C75: Cust_75 | D75: Bulk | E75: Cloud Kitchen | F75: Delhi | G75: 606047 | H75: Phonepe | I75: SKU75 | J75: Product_75 | K75: Baby | L75: 4 | M75: 93.21 | N75: 9.32 | O75: 363.52 | P75: 18.18 | Q75: 20 | R75: 10 | S75: 411.7 | T75: 24.67 | U75: =TEXT(B75,"dddd") -> Tuesday
A76: O0077 | B76: 14-01-2025 | C76: Cust_76 | D76: New | E76: Household | F76: Bangalore | G76: 872800 | H76: Upi | I76: SKU76 | J76: Product_76 | K76: Beverages | L76: 3 | M76: 98.22 | N76: 0 | O76: 294.66 | P76: 14.73 | Q76: 20 | R76: 10 | S76: 339.39 | T76: 26 | U76: =TEXT(B76,"dddd") -> Tuesday
A77: O0078 | B77: 17-01-2025 | C77: Cust_77 | D77: Bulk | E77: Tea Stall | F77: Bangalore | G77: 842406 | H77: Upi | I77: SKU77 | J77: Product_77 | K77: Veg | L77: 1 | M77: 234.65 | N77: 35.2 | O77: 199.45 | P77: 9.97 | Q77: 30 | R77: 20 | S77: 259.42 | T77: 28 | U77: =TEXT(B77,"dddd") -> Friday
A78: O0079 | B78: 05-02-2025 | C78: Cust_78 | D78: Bulk | E78: Café | F78: Bangalore | H78: Netbanking | I78: SKU78 | J78: Product_78 | K78: Beverages | L78: 1 | M78: 188.2 | N78: 28.23 | O78: 159.97 | P78: 8 | Q78: 30 | R78: 15 | S78: 212.97 | T78: 20 | U78: =TEXT(B78,"dddd") -> Wednesday
A79: O0080 | B79: 19-02-2025 | C79: Cust_79 | D79: Bulk | E79: Office | F79: Delhi | G79: 713474 | H79: Upi | I79: SKU79 | J79: Product_79 | K79: Snacks | L79: 1 | M79: 232.87 | N79: 11.64 | O79: 221.23 | P79: 11.06 | Q79: 20 | R79: 5 | S79: 257.29 | T79: 31 | U79: =TEXT(B79,"dddd") -> Wednesday
A80: O0081 | B80: 09-02-2025 | C80: Cust_80 | D80: Bulk | E80: Café | F80: Mumbai | G80: 438076 | H80: Upi | I80: SKU80 | J80: Product_80 | K80: Fruits | L80: 2 | M80: 46.21 | N80: 0 | O80: 92.42 | P80: 4.62 | Q80: 20 | R80: 5 | S80: 122.04 | T80: 24.67 | U80: =TEXT(B80,"dddd") -> Sunday
A81: O0082 | B81: 04-01-2025 | C81: Cust_81 | D81: Bulk | E81: Café | F81: Delhi | G81: 440941 | H81: Cod | I81: SKU81 | J81: Product_81 | K81: Baby | L81: 2 | M81: 170.05 | N81: 0 | O81: 340.1 | P81: 17.01 | Q81: 30 | R81: 15 | S81: 402.11 | T81: 20 | U81: =TEXT(B81,"dddd") -> Saturday
A82: O0083 | B82: 02-01-2025 | C82: Cust_82 | D82: New | E82: Household | F82: Delhi | G82: 312943 | H82: Upi | I82: SKU82 | J82: Product_82 | K82: Other | L82: 2 | M82: 98.72 | N82: 4.94 | O82: 192.5 | P82: 9.62 | Q82: 0 | R82: 5 | S82: 207.12 | T82: 31 | U82: =TEXT(B82,"dddd") -> Thursday
A83: O0084 | B83: 06-01-2025 | C83: Cust_83 | D83: Bulk | E83: Cloud Kitchen | F83: Bangalore | G83: 762784 | H83: Wallet | I83: SKU83 | J83: Product_83 | K83: Dairy | L83: 2 | M83: 99.38 | N83: 14.91 | O83: 183.85 | P83: 9.19 | Q83: 10 | R83: 10 | S83: 213.04 | T83: 40 | U83: =TEXT(B83,"dddd") -> Monday
A84: O0085 | B84: 23-02-2025 | C84: Cust_84 | D84: Returning | E84: Household | F84: Bangalore | H84: Upi | I84: SKU84 | J84: Product_84 | K84: Other | L84: 5 | M84: 64.24 | N84: 0 | O84: 321.2 | P84: 16.06 | Q84: 30 | R84: 10 | S84: 377.26 | T84: 12 | U84: =TEXT(B84,"dddd") -> Sunday
A85: O0086 | B85: 11-02-2025 | C85: Cust_85 | D85: Returning | E85: Household | F85: Bangalore | H85: Upi | I85: SKU85 | J85: Product_85 | K85: Beverages | L85: 5 | M85: 115.07 | N85: 0 | O85: 575.35 | P85: 28.77 | Q85: 30 | R85: 0 | S85: 634.12 | T85: 36 | U85: =TEXT(B85,"dddd") -> Tuesday
A86: O0087 | B86: 04-01-2025 | C86: Cust_86 | D86: Bulk | E86: Café | F86: Bangalore | G86: 343373 | H86: Phonepe | I86: SKU86 | J86: Product_86 | K86: Beverages | L86: 2 | M86: 91.09 | N86: 4.55 | O86: 177.63 | P86: 8.88 | Q86: 30 | R86: 10 | S86: 226.51 | T86: 32 | U86: =TEXT(B86,"dddd") -> Saturday
A87: O0088 | B87: 23-02-2025 | C87: Cust_87 | D87: Bulk | E87: Tea Stall | F87: Bangalore | G87: 707167 | H87: Gpay | I87: SKU87 | J87: Product_87 | K87: Beverages | L87: 4 | M87: 97.79 | N87: 9.78 | O87: 381.38 | P87: 19.07 | Q87: 20 | R87: 10 | S87: 430.45 | T87: 25 | U87: =TEXT(B87,"dddd") -> Sunday
A88: O0089 | B88: 29-01-2025 | C88: Cust_88 | D88: Bulk | E88: Cloud Kitchen | F88: Bangalore | G88: 430904 | H88: Gpay | I88: SKU88 | J88: Product_88 | K88: Veg | L88: 4 | M88: 104.59 | N88: 10.46 | O88: 407.9 | P88: 20.4 | Q88: 10 | R88: 0 | S88: 438.3 | T88: 37 | U88: =TEXT(B88,"dddd") -> Wednesday
A89: O0090 | B89: 18-01-2025 | C89: Cust_89 | D89: Bulk | E89: Café | F89: Bangalore | G89: 466245 | H89: Netbanking | I89: SKU89 | J89: Product_89 | K89: Dairy | L89: 3 | M89: 34.43 | N89: 5.16 | O89: 98.13 | P89: 4.91 | Q89: 30 | R89: 15 | S89: 148.04 | T89: 31 | U89: =TEXT(B89,"dddd") -> Saturday
A90: O0091 | B90: 26-01-2025 | C90: Cust_90 | D90: Bulk | E90: Tea Stall | F90: Mumbai | G90: 891541 | H90: Wallet | I90: SKU90 | J90: Product_90 | K90: Essentials | L90: 1 | M90: 92.14 | N90: 9.21 | O90: 82.93 | P90: 4.15 | Q90: 30 | R90: 5 | S90: 122.08 | T90: 24.67 | U90: =TEXT(B90,"dddd") -> Sunday
A91: O0092 | B91: 13-02-2025 | C91: Cust_91 | D91: Bulk | E91: Bakery | F91: Mumbai | G91: 726759 | H91: Phonepe | I91: SKU91 | J91: Product_91 | K91: Dairy | L91: 4 | M91: 16.93 | N91: 0 | O91: 67.72 | P91: 3.39 | Q91: 30 | R91: 10 | S91: 111.11 | T91: 20 | U91: =TEXT(B91,"dddd") -> Thursday
A92: O0093 | B92: 03-02-2025 | C92: Cust_92 | D92: Returning | E92: Household | F92: Delhi | G92: 969741 | H92: Netbanking | I92: SKU92 | J92: Product_92 | K92: Fruits | L92: 1 | M92: 237.77 | N92: 35.67 | O92: 202.1 | P92: 10.11 | Q92: 30 | R92: 5 | S92: 247.21 | T92: 21 | U92: =TEXT(B92,"dddd") -> Monday
A93: O0094 | B93: 10-01-2025 | C93: Cust_93 | D93: Bulk | E93: Tea Stall | F93: Mumbai | G93: 693586 | H93: Phonepe | I93: SKU93 | J93: Product_93 | K93: Essentials | L93: 5 | M93: 164.53 | N93: 16.45 | O93: 806.2 | P93: 40.31 | Q93: 30 | R93: 15 | S93: 891.51 | T93: 27 | U93: =TEXT(B93,"dddd") -> Friday
A94: O0095 | B94: 05-02-2025 | C94: Cust_94 | D94: Bulk | E94: Café | F94: Delhi | G94: 545485 | H94: Gpay | I94: SKU94 | J94: Product_94 | K94: Essentials | L94: 3 | M94: 104.2 | N94: 15.63 | O94: 296.97 | P94: 14.85 | Q94: 10 | R94: 5 | S94: 326.82 | T94: 20 | U94: =TEXT(B94,"dddd") -> Wednesday
A95: O0096 | B95: 14-01-2025 | C95: Cust_95 | D95: Returning | E95: Household | F95: Delhi | G95: 830023 | H95: Cod | I95: SKU95 | J95: Product_95 | K95: Dairy | L95: 2 | M95: 50.5 | N95: 0 | O95: 101 | P95: 5.05 | Q95: 20 | R95: 0 | S95: 126.05 | T95: 18 | U95: =TEXT(B95,"dddd") -> Tuesday
A96: O0097 | B96: 31-01-2025 | C96: Cust_96 | D96: Bulk | E96: Tea Stall | F96: Bangalore | G96: 999187 | H96: Phonepe | I96: SKU96 | J96: Product_96 | K96: Baby | L96: 1 | M96: 67.42 | N96: 3.37 | O96: 64.05 | P96: 3.2 | Q96: 10 | R96: 5 | S96: 82.25 | T96: 25 | U96: =TEXT(B96,"dddd") -> Friday
A97: O0098 | B97: 17-02-2025 | C97: Cust_97 | D97: Bulk | E97: Tea Stall | F97: Bangalore | G97: 312977 | H97: Upi | I97: SKU97 | J97: Product_97 | K97: Frozen | L97: 1 | M97: 53.56 | N97: 0 | O97: 53.56 | P97: 2.68 | Q97: 20 | R97: 5 | S97: 81.24 | T97: 42 | U97: =TEXT(B97,"dddd") -> Monday
... A100: O0101 | B100: 14-01-2025 | C100: Cust_100 | D100: Bulk | E100: Office | F100: Bangalore | G100: 649114 | H100: Upi | I100: SKU100 | J100: Product_100 | K100: Frozen | L100: 1 | M100: 195.91 | N100: 29.39 | O100: 166.52 | P100: 8.33 | Q100: 20 | R100: 15 | S100: 209.85 | T100: 24.67 | U100: =TEXT(B100,"dddd") -> Tuesday
A101: O0102 | B101: 23-01-2025 | C101: Cust_101 | D101: Bulk | E101: Café | F101: Mumbai | H101: Upi | I101: SKU101 | J101: Product_101 | K101: Beverages | L101: 4 | M101: 246.95 | N101: 0 | O101: 987.8 | P101: 49.39 | Q101: 20 | R101: 5 | S101: 1062.19 | T101: 22 | U101: =TEXT(B101,"dddd") -> Thursday
A102: O0103 | B102: 01-03-2025 | C102: Cust_102 | D102: Bulk | E102: Tea Stall | F102: Mumbai | G102: 920094 | H102: Phonepe | I102: SKU102 | J102: Product_102 | K102: Veg | L102: 5 | M102: 131.86 | N102: 6.59 | O102: 652.71 | P102: 32.64 | Q102: 0 | R102: 15 | S102: 700.35 | T102: 24.67 | U102: =TEXT(B102,"dddd") -> Saturday
A103: O0104 | B103: 26-02-2025 | C103: Cust_103 | D103: Bulk | E103: Café | F103: Delhi | G103: 172715 | H103: Upi | I103: SKU103 | J103: Product_103 | K103: Beverages | L103: 3 | M103: 250.95 | N103: 25.09 | O103: 727.76 | P103: 36.39 | Q103: 20 | R103: 5 | S103: 789.15 | T103: 41 | U103: =TEXT(B103,"dddd") -> Wednesday
A104: O0105 | B104: 09-02-2025 | C104: Cust_104 | D104: Bulk | E104: Cloud Kitchen | F104: Bangalore | G104: 183186 | H104: Gpay | I104: SKU104 | J104: Product_104 | K104: Beverages | L104: 2 | M104: 80.91 | N104: 4.05 | O104: 157.77 | P104: 7.89 | Q104: 0 | R104: 15 | S104: 180.66 | T104: 20 | U104: =TEXT(B104,"dddd") -> Sunday
A105: O0106 | B105: 21-01-2025 | C105: Cust_105 | D105: Bulk | E105: Cloud Kitchen | F105: Delhi | G105: 320971 | H105: Upi | I105: SKU105 | J105: Product_105 | K105: Frozen | L105: 1 | M105: 88.24 | N105: 8.82 | O105: 79.42 | P105: 3.97 | Q105: 0 | R105: 5 | S105: 88.39 | T105: 19 | U105: =TEXT(B105,"dddd") -> Tuesday
A106: O0107 | B106: 16-01-2025 | C106: Cust_106 | D106: Bulk | E106: Tea Stall | F106: Bangalore | G106: 268484 | H106: Card | I106: SKU106 | J106: Product_106 | K106: Fruits | L106: 2 | M106: 223.65 | N106: 33.55 | O106: 413.75 | P106: 20.69 | Q106: 0 | R106: 15 | S106: 449.44 | T106: 24.67 | U106: =TEXT(B106,"dddd") -> Thursday
A107: O0108 | B107: 14-02-2025 | C107: Cust_107 | D107: Bulk | E107: Café | F107: Bangalore | G107: 538716 | H107: Upi | I107: SKU107 | J107: Product_107 | K107: Frozen | L107: 3 | M107: 52.33 | N107: 7.85 | O107: 149.14 | P107: 7.46 | Q107: 20 | R107: 0 | S107: 176.6 | T107: 30 | U107: =TEXT(B107,"dddd") -> Friday
A108: O0109 | B108: 18-01-2025 | C108: Cust_108 | D108: Bulk | E108: Cloud Kitchen | F108: Mumbai | G108: 331447 | H108: Cod | I108: SKU108 | J108: Product_108 | K108: Beverages | L108: 2 | M108: 19.88 | N108: 2.98 | O108: 36.78 | P108: 1.84 | Q108: 0 | R108: 5 | S108: 43.62 | T108: 24 | U108: =TEXT(B108,"dddd") -> Saturday
A109: O0110 | B109: 16-02-2025 | C109: Cust_109 | D109: Bulk | E109: Bakery | F109: Bangalore | G109: 726045 | H109: Gpay | I109: SKU109 | J109: Product_109 | K109: Veg | L109: 4 | M109: 8.14 | N109: 1.22 | O109: 31.34 | P109: 1.57 | Q109: 20 | R109: 15 | S109: 67.91 | T109: 15 | U109: =TEXT(B109,"dddd") -> Sunday
A110: O0111 | B110: 22-02-2025 | C110: Cust_110 | D110: Bulk | E110: Bakery | F110: Mumbai | G110: 667873 | H110: Netbanking | I110: SKU110 | J110: Product_110 | K110: Baby | L110: 3 | M110: 182.83 | N110: 27.42 | O110: 521.07 | P110: 26.05 | Q110: 20 | R110: 0 | S110: 567.12 | T110: 24 | U110: =TEXT(B110,"dddd") -> Saturday
A111: O0112 | B111: 24-01-2025 | C111: Cust_111 | D111: Bulk | E111: Café | F111: Mumbai | G111: 915858 | H111: Phonepe | I111: SKU111 | J111: Product_111 | K111: Fruits | L111: 2 | M111: 199.02 | N111: 19.9 | O111: 378.14 | P111: 18.91 | Q111: 30 | R111: 20 | S111: 447.05 | T111: 29 | U111: =TEXT(B111,"dddd") -> Friday
A112: O0113 | B112: 26-01-2025 | C112: Cust_112 | D112: Returning | E112: Household | F112: Mumbai | G112: 360116 | H112: Upi | I112: SKU112 | J112: Product_112 | K112: Baby | L112: 4 | M112: 130.76 | N112: 19.61 | O112: 503.43 | P112: 25.17 | Q112: 30 | R112: 0 | S112: 558.6 | T112: 18 | U112: =TEXT(B112,"dddd") -> Sunday
A113: O0114 | B113: 25-01-2025 | C113: Cust_113 | D113: Returning | E113: Household | F113: Bangalore | G113: 257795 | H113: Upi | I113: SKU113 | J113: Product_113 | K113: Fruits | L113: 1 | M113: 82.47 | N113: 8.25 | O113: 74.22 | P113: 3.71 | Q113: 0 | R113: 10 | S113: 87.93 | T113: 28 | U113: =TEXT(B113,"dddd") -> Saturday
... A158: O0159 | B158: 09-02-2025 | C158: Cust_158 | D158: Bulk | E158: Cloud Kitchen | F158: Mumbai | G158: 942186 | H158: Upi | I158: SKU158 | J158: Product_158 | K158: Snacks | L158: 4 | M158: 220.66 | N158: 33.1 | O158: 849.54 | P158: 42.48 | Q158: 20 | R158: 15 | S158: 927.02 | T158: 19 | U158: =TEXT(B158,"dddd") -> Sunday
A159: O0160 | B159: 22-01-2025 | C159: Cust_159 | D159: Bulk | E159: Bakery | F159: Mumbai | H159: Netbanking | I159: SKU159 | J159: Product_159 | K159: Frozen | L159: 3 | M159: 87.95 | N159: 8.79 | O159: 255.06 | P159: 12.75 | Q159: 30 | R159: 5 | S159: 302.81 | T159: 26 | U159: =TEXT(B159,"dddd") -> Wednesday
A160: O0161 | B160: 27-01-2025 | C160: Cust_160 | D160: Bulk | E160: Bakery | F160: Mumbai | H160: Cod | I160: SKU160 | J160: Product_160 | K160: Essentials | L160: 3 | M160: 168.57 | N160: 16.86 | O160: 488.85 | P160: 24.44 | Q160: 10 | R160: 20 | S160: 543.29 | T160: 11 | U160: =TEXT(B160,"dddd") -> Monday
A161: O0162 | B161: 04-02-2025 | C161: Cust_161 | D161: Returning | E161: Household | F161: Delhi | G161: 216492 | H161: Upi | I161: SKU161 | J161: Product_161 | K161: Frozen | L161: 1 | M161: 59.11 | N161: 5.91 | O161: 53.2 | P161: 2.66 | Q161: 20 | R161: 10 | S161: 85.86 | T161: 36 | U161: =TEXT(B161,"dddd") -> Tuesday
A162: O0163 | B162: 01-01-2025 | C162: Cust_162 | D162: Bulk | E162: Cloud Kitchen | F162: Bangalore | G162: 561227 | H162: Upi | I162: SKU162 | J162: Product_162 | K162: Fruits | L162: 1 | M162: 74.46 | N162: 7.45 | O162: 67.01 | P162: 3.35 | Q162: 0 | R162: 15 | S162: 85.36 | T162: 25 | U162: =TEXT(B162,"dddd") -> Wednesday
A163: O0164 | B163: 04-02-2025 | C163: Cust_163 | D163: New | E163: Household | F163: Mumbai | G163: 599499 | H163: Cod | I163: SKU163 | J163: Product_163 | K163: Beverages | L163: 3 | M163: 26.65 | N163: 4 | O163: 75.95 | P163: 3.8 | Q163: 10 | R163: 10 | S163: 99.75 | T163: 41 | U163: =TEXT(B163,"dddd") -> Tuesday
A164: O0165 | B164: 06-02-2025 | C164: Cust_164 | D164: New | E164: Household | F164: Delhi | G164: 498465 | H164: Upi | I164: SKU164 | J164: Product_164 | K164: Beverages | L164: 4 | M164: 49.64 | N164: 2.48 | O164: 196.08 | P164: 9.8 | Q164: 20 | R164: 0 | S164: 225.88 | T164: 12 | U164: =TEXT(B164,"dddd") -> Thursday
A165: O0166 | B165: 16-02-2025 | C165: Cust_165 | D165: Bulk | E165: Tea Stall | F165: Bangalore | G165: 415507 | H165: Phonepe | I165: SKU165 | J165: Product_165 | K165: Veg | L165: 6 | M165: 145.14 | N165: 7.26 | O165: 863.58 | P165: 43.18 | Q165: 10 | R165: 20 | S165: 936.76 | T165: 24.67 | U165: =TEXT(B165,"dddd") -> Sunday
A166: O0167 | B166: 14-01-2025 | C166: Cust_166 | D166: New | E166: Household | F166: Mumbai | G166: 142828 | H166: Gpay | I166: SKU166 | J166: Product_166 | K166: Other | L166: 3 | M166: 79.15 | N166: 7.92 | O166: 229.53 | P166: 11.48 | Q166: 30 | R166: 5 | S166: 276.01 | T166: 24.67 | U166: =TEXT(B166,"dddd") -> Tuesday
A167: O0168 | B167: 03-01-2025 | C167: Cust_167 | D167: Bulk | E167: Office | F167: Delhi | G167: 886639 | H167: Card | I167: SKU167 | J167: Product_167 | K167: Beverages | L167: 5 | M167: 161.66 | N167: 8.08 | O167: 800.22 | P167: 40.01 | Q167: 30 | R167: 10 | S167: 880.23 | T167: 24.67 | U167: =TEXT(B167,"dddd") -> Friday
A168: O0169 | B168: 01-01-2025 | C168: Cust_168 | D168: Bulk | E168: Bakery | F168: Bangalore | G168: 601643 | H168: Upi | I168: SKU168 | J168: Product_168 | K168: Fruits | L168: 1 | M168: 10.69 | N168: 1.07 | O168: 9.62 | P168: 0.48 | Q168: 20 | R168: 10 | S168: 40.1 | T168: 17 | U168: =TEXT(B168,"dddd") -> Wednesday
A169: O0170 | B169: 05-01-2025 | C169: Cust_169 | D169: Bulk | E169: Bakery | F169: Mumbai | G169: 198540 | H169: Phonepe | I169: SKU169 | J169: Product_169 | K169: Dairy | L169: 5 | M169: 118.8 | N169: 11.88 | O169: 582.12 | P169: 29.11 | Q169: 0 | R169: 20 | S169: 631.23 | T169: 28 | U169: =TEXT(B169,"dddd") -> Sunday
A170: O0171 | B170: 26-01-2025 | C170: Cust_170 | D170: Bulk | E170: Office | F170: Delhi | G170: 156273 | H170: Upi | I170: SKU170 | J170: Product_170 | K170: Veg | L170: 1 | M170: 167.36 | N170: 25.1 | O170: 142.26 | P170: 7.11 | Q170: 0 | R170: 10 | S170: 159.37 | T170: 48 | U170: =TEXT(B170,"dddd") -> Sunday
A171: O0172 | B171: 24-02-2025 | C171: Cust_171 | D171: Bulk | E171: Tea Stall | F171: Delhi | G171: 110699 | H171: Wallet | I171: SKU171 | J171: Product_171 | K171: Frozen | L171: 3 | M171: 145.51 | N171: 0 | O171: 436.53 | P171: 21.83 | Q171: 20 | R171: 10 | S171: 488.36 | T171: 28 | U171: =TEXT(B171,"dddd") -> Monday
...

Sheet KPI
A1: TOTAL SALES | B1: =SUM(Sheet2!S2:S1499) -> 563284.75 | C1: SUM
A2: TOTAL PRODUCTS | B2: =COUNTA(_xlfn.UNIQUE(Sheet2!J2:J1499)) -> 200 | C2: COUNT UNIQUE
A3: TOTAL SKU'S | B3: =COUNTA(_xlfn.UNIQUE(Sheet2!I2:I1499)) -> 200 | C3: COUNT UNIQUE
A4: TOTAL ORDERS | B4: =COUNTA(_xlfn.UNIQUE(Sheet2!A2:A1499)) -> 1498 | C4: COUNTA
A5: AVG DELIVERY TIME | B5: =AVERAGE(Sheet2!T2:T1499) -> 24.671215 | C5: AVERAGE

Sheet CHARTS
A1: CREATE A CHART TO SHOW THE SALES OVER DIFFERENT WEEKDAYS
A3: Row Labels | B3: Sum of Sales
A4: Sunday | B4: 89688.34
A5: Monday | B5: 63297.72
A6: Tuesday | B6: 69215.7
A7: Wednesday | B7: 89028.19
A8: Thursday | B8: 91118.9
A9: Friday | B9: 75665.63
A10: Saturday | B10: 85270.27
A11: Grand Total | B11: 563284.75
A18: CREATE A CHART TO SHOW TOP 10 PRODUCTS
A20: Row Labels | B20: Sum of Sales
A21: Product_102 | B21: 4361.11
A22: Product_12 | B22: 4753.83
A23: Product_13 | B23: 4338.5
A24: Product_139 | B24: 5111.6
A25: Product_160 | B25: 4726.73
A26: Product_18 | B26: 4194.36
A27: Product_198 | B27: 4337.62
A28: Product_30 | B28: 5188.17
A29: Product_84 | B29: 4399.39
A30: Product_85 | B30: 4295.97
A31: Grand Total | B31: 45707.28
A37: CREATE A CHART TO SHOW | C37: BOTTOM 1O SKU'S
A40: Row Labels | B40: Sum of Sales
A41: SKU104 | B41: 1447.2
A42: SKU107 | B42: 1531.74
A43: SKU119 | B43: 1531.49
A44: SKU135 | B44: 1108.3
A45: SKU151 | B45: 1529.18
A46: SKU168 | B46: 1113.35
A47: SKU186 | B47: 1316.78
A48: SKU188 | B48: 1413.18
A49: SKU189 | B49: 1294.92
A50: SKU42 | B50: 1469.34
A51: Grand Total | B51: 13755.48
A57: CREATE A CHART TO SHOW THE CONTRIBUTION OF SALES BY EACH CITY
A59: Row Labels | B59: Sum of Sales
A60: Bangalore | B60: 201528.98
A61: Delhi | B61: 180200.31
A62: Mumbai | B62: 169384.46
A63: N/A | B63: 12171
A64: Grand Total | B64: 563284.75
A74: CREATE A CHART TO SHOW MAXIMUM DELIVERY TIME BY CITY
A77: Row Labels | B77: Sum of Delivery_Time
A78: Bangalore | B78: 12613.6
A79: Delhi | B79: 12226.93
A80: Mumbai | B80: 11418.93
A81: N/A | B81: 698.02
A82: Grand Total | B82: 36957.48
A92: CREATE A CHART TO SHOW SALES BY DIFFERENT CATEGORIES
A95: Row Labels | B95: Sum of Sales
A96: Baby | B96: 34273.77
A97: Bakery | B97: 29579.42
A98: Beverages | B98: 82603.27
A99: Dairy | B99: 61073.33
A100: Essentials | B100: 36990.66
A101: Frozen | B101: 75706.82
A102: Fruits | B102: 61343.1
A103: Other | B103: 35419.25
A104: Snacks | B104: 72712.83
A105: Veg | B105: 73582.3
A106: Grand Total | B106: 563284.75
A111: CREATE A CHART TO SHOW NUMBER OF CUSTOMER BY EACH CUSTOMER SEGMENT
A114: Row Labels | B114: Count of Customer_Name
A115: Bakery | B115: 226
A116: Café | B116: 241
A117: Cloud Kitchen | B117: 258
A118: Household | B118: 253
A119: Office | B119: 272
A120: Tea Stall | B120: 248
A121: Grand Total | B121: 1498

Sheet REPORTS
